tkmessagebox/__init__.py
TkinterMessagebox-1.0.1.dist-info/METADATA
TkinterMessagebox-1.0.1.dist-info/WHEEL
TkinterMessagebox-1.0.1.dist-info/top_level.txt
TkinterMessagebox-1.0.1.dist-info/zip-safe
TkinterMessagebox-1.0.1.dist-info/RECORD
